koalafolio/KoalaIcon.png
koalafolio/__init__.py
koalafolio/__main__.py
koalafolio/gui_root.py
koalafolio/koalaicon.ico
koalafolio/Import/Converter.py
koalafolio/Import/Models.py
koalafolio/Import/RegexPatterns.py
koalafolio/Import/TradeImporter.py
koalafolio/Import/__init__.py
koalafolio/Import/apiImport.py
koalafolio/Import/defaultApiData.db
koalafolio/PcpCore/__init__.py
koalafolio/PcpCore/arguments.py
koalafolio/PcpCore/core.py
koalafolio/PcpCore/logger.py
koalafolio/PcpCore/settings.py
koalafolio/exp/QTranslate.py
koalafolio/exp/__init__.py
koalafolio/exp/profitExport.py
koalafolio/graphics/delete.png
koalafolio/graphics/export.png
koalafolio/graphics/import.png
koalafolio/graphics/koalaicon.ico
koalafolio/graphics/left.png
koalafolio/graphics/portfolio.png
koalafolio/graphics/right.png
koalafolio/graphics/settings.png
koalafolio/graphics/trades.png
koalafolio/gui/QApiImport.py
koalafolio/gui/QThreads.py
koalafolio/gui/__init__.py
koalafolio/gui/helper/LazyPageLoader.py
koalafolio/gui/helper/QLogger.py
koalafolio/gui/helper/QSettings.py
koalafolio/gui/helper/QStyle.py
koalafolio/gui/helper/__init__.py
koalafolio/gui/pages/ExportPage.py
koalafolio/gui/pages/ImportPage.py
koalafolio/gui/pages/PortfolioPage.py
koalafolio/gui/pages/Qpages.py
koalafolio/gui/pages/SettingsPage.py
koalafolio/gui/pages/TradesPage.py
koalafolio/gui/pages/__init__.py
koalafolio/gui/widgets/FilterableHeader.py
koalafolio/gui/widgets/FilterableTable.py
koalafolio/gui/widgets/ProfitBarChart.py
koalafolio/gui/widgets/QCharts.py
koalafolio/gui/widgets/QCompleterComboBox.py
koalafolio/gui/widgets/QFilterableComboBox.py
koalafolio/gui/widgets/QLoggerWidget.py
koalafolio/gui/widgets/QPortfolioTable.py
koalafolio/gui/widgets/QTradeTable.py
koalafolio/gui/widgets/Qcontrols.py
koalafolio/gui/widgets/ScrollableTable.py
koalafolio/gui/widgets/__init__.py
koalafolio/web/__init__.py
koalafolio/web/chaindata.py
koalafolio/web/coingeckoApi.py
koalafolio/web/cryptocompare.py
koalafolio-0.12.8.dist-info/licenses/LICENSE
koalafolio-0.12.8.dist-info/METADATA
koalafolio-0.12.8.dist-info/WHEEL
koalafolio-0.12.8.dist-info/entry_points.txt
koalafolio-0.12.8.dist-info/top_level.txt
koalafolio-0.12.8.dist-info/RECORD
