Metadata-Version: 2.4
Name: koalafolio
Version: 0.12.8
Summary: portfolio app for crypto trading and tax reporting
Home-page: https://gitea.com/2martin2/koalafolio
Author: 2martin2
Author-email: koala+pypi@slmail.me
License: GPL-3.0
Keywords: crypto cryptocoins tax portfolio tracking
Classifier: Programming Language :: Python :: 3
Requires-Python: >=3.7
License-File: LICENSE
Requires-Dist: ccxt
Requires-Dist: openpyxl
Requires-Dist: pandas>=1.5.3
Requires-Dist: pycoingecko<=2.3.0
Requires-Dist: pycryptodomex
Requires-Dist: pyqt5
Requires-Dist: pyqtchart
Requires-Dist: requests
Requires-Dist: tzlocal>=5.0.1
Requires-Dist: xlrd
Dynamic: author
Dynamic: author-email
Dynamic: classifier
Dynamic: description
Dynamic: description-content-type
Dynamic: home-page
Dynamic: keywords
Dynamic: license
Dynamic: license-file
Dynamic: requires-dist
Dynamic: requires-python
Dynamic: summary
